ct_util/__init__.py
ct_util/ct_util.py
ct_util_tools-0.1.1.dist-info/WHEEL
ct_util_tools-0.1.1.dist-info/METADATA
ct_util_tools-0.1.1.dist-info/RECORD
