Metadata-Version: 2.1
Name: ct-util-tools
Version: 0.1.1
Summary: 
Author: Chris Tran
Author-email: chris.l.tran.2016@gmail.com
Requires-Python: >=3.10,<4.0
Classifier: Programming Language :: Python :: 3
Classifier: Programming Language :: Python :: 3.10
Classifier: Programming Language :: Python :: 3.11
Requires-Dist: numpy (>=1.24.1,<2.0.0)
Requires-Dist: pandas (>=1.5.2,<2.0.0)
